easysched/__init__.py
easysched/command.py
easysched/control.py
easysched/daemon.py
easysched/server.py
easysched/state.py
easysched/task.py
easysched/tools/Config.py
easysched/tools/Lock.py
easysched/tools/Logging.py
easysched/tools/__init__.py
easysched/tools/config.py
easysched/tools/lock.py
easysched/tools/logging.py
easysched-1.2.9.data/data/share/easysched/session_simple/easysched.service
easysched-1.2.9.data/data/share/easysched/session_simple/example.cfg
easysched-1.2.9.data/data/share/easysched/session_xserver/easysched.service
easysched-1.2.9.data/data/share/easysched/session_xserver/example.cfg
easysched-1.2.9.dist-info/METADATA
easysched-1.2.9.dist-info/RECORD
easysched-1.2.9.dist-info/WHEEL
easysched-1.2.9.dist-info/entry_points.txt
easysched-1.2.9.dist-info/top_level.txt
