Metadata-Version: 2.1
Name: easysched
Version: 1.2.9
Summary: Lightweight framework to easily schedule multiple tasks.
Home-page: UNKNOWN
Author: Lars Klitzke
Author-email: Lars@klitzke-web.de
License: UNKNOWN
Platform: UNKNOWN
Classifier: Operating System :: OS Independent
Classifier: Programming Language :: Python :: 3.5
Classifier: Programming Language :: Python :: 3.6
Classifier: Programming Language :: Python :: 3.7
Classifier: License :: OSI Approved :: GNU Lesser General Public License v3 or later (LGPLv3+)
Classifier: Topic :: Software Development :: Libraries :: Application Frameworks
Classifier: Natural Language :: English
Classifier: Intended Audience :: Developers
Requires-Dist: psutil
